{"status": "OK", "bill": {"bill_id": 1451103, "change_hash": "30a11641a107ac421e4184fbfc7ddb20", "session_id": 1791, "session": {"session_id": 1791, "state_id": 5, "year_start": 2021, "year_end": 2022, "prefile": 0, "sine_die": 0, "prior": 0, "special": 0, "session_tag": "Regular Session", "session_title": "2021-2022 Regular Session", "session_name": "2021-2022 Session"}, "url": "https://legiscan.com/CA/bill/SB406/2021", "state_link": "https://leginfo.legislature.ca.gov/faces/billStatusClient.xhtml?bill_id=202120220SB406", "completed": 1, "status": 4, "status_date": "2021-10-08", "progress": [{"date": "2021-02-12", "event": 1}, {"date": "2021-02-25", "event": 9}, {"date": "2021-04-05", "event": 9}, {"date": "2021-04-13", "event": 10}, {"date": "2021-04-13", "event": 9}, {"date": "2021-05-20", "event": 10}, {"date": "2021-06-02", "event": 2}, {"date": "2021-06-10", "event": 9}, {"date": "2021-07-12", "event": 10}, {"date": "2021-07-13", "event": 9}, {"date": "2021-08-26", "event": 10}, {"date": "2021-09-10", "event": 3}, {"date": "2021-10-08", "event": 8}, {"date": "2021-10-08", "event": 4}], "state": "CA", "state_id": 5, "bill_number": "SB406", "bill_type": "B", "bill_type_id": "1", "body": "S", "body_id": 20, "current_body": "S", "current_body_id": 20, "title": "Oil and gas: operations: notice of intention: investigations: data availability.", "description": "An act to amend Sections 3213, 3227, 3235, and 3412 of, to amend the heading of Article 3 (commencing with Section 690) of Chapter 2 of Division 1 of, and to add Sections 3108.5, 3115, and 3203.5 to, the Public Resources Code, relating to oil and gas.", "pending_committee_id": 0, "committee": [], "referrals": [{"date": "2021-02-12", "committee_id": 489, "chamber": "S", "chamber_id": 20, "name": "Rules"}, {"date": "2021-02-25", "committee_id": 485, "chamber": "S", "chamber_id": 20, "name": "Natural Resources and Water"}, {"date": "2021-04-13", "committee_id": 475, "chamber": "S", "chamber_id": 20, "name": "Appropriations"}, {"date": "2021-06-10", "committee_id": 466, "chamber": "A", "chamber_id": 19, "name": "Natural Resources"}, {"date": "2021-07-12", "committee_id": 449, "chamber": "A", "chamber_id": 19, "name": "Appropriations"}], "history": [{"date": "2021-02-12", "action": "Introduced. Read first time. To Com. on RLS. for assignment. To print.", "chamber": "S", "chamber_id": 20, "importance": 1}, {"date": "2021-02-16", "action": "From printer. May be acted upon on or after March 18.", "chamber": "S", "chamber_id": 20, "importance": 0}, {"date": "2021-02-22", "action": "Art. IV. Sec. 8(a) of the Constitution dispensed with.", "chamber": "S", "chamber_id": 20, "importance": 0}, {"date": "2021-02-22", "action": "(Ayes 32. Noes 4.)", "chamber": "S", "chamber_id": 20, "importance": 0}, {"date": "2021-02-22", "action": "Joint Rule 55 suspended. (Ayes 32. Noes 4. Page 272.)", "chamber": "S", "chamber_id": 20, "importance": 0}, {"date": "2021-02-25", "action": "Referred to Com. on N.R. & W.", "chamber": "S", "chamber_id": 20, "importance": 1}, {"date": "2021-03-24", "action": "Set for hearing April 13.", "chamber": "S", "chamber_id": 20, "importance": 0}, {"date": "2021-04-05", "action": "From committee with author's amendments. Read second time and amended. Re-referred to Com. on N.R. & W.", "chamber": "S", "chamber_id": 20, "importance": 1}, {"date": "2021-04-13", "action": "From committee: Do pass and re-refer to Com. on APPR. (Ayes 7. Noes 0. Page 776.) (April 13). Re-referred to Com. on APPR.", "chamber": "S", "chamber_id": 20, "importance": 1}, {"date": "2021-04-20", "action": "April 19 hearing: Placed on APPR suspense file.", "chamber": "S", "chamber_id": 20, "importance": 0}, {"date": "2021-05-14", "action": "Set for hearing May 20.", "chamber": "S", "chamber_id": 20, "importance": 0}, {"date": "2021-05-20", "action": "From committee: Do pass as amended. (Ayes 6. Noes 0. Page 1190.) (May 20).", "chamber": "S", "chamber_id": 20, "importance": 1}, {"date": "2021-05-20", "action": "Read second time and amended. Ordered to second reading.", "chamber": "S", "chamber_id": 20, "importance": 0}, {"date": "2021-05-24", "action": "Read second time. Ordered to third reading.", "chamber": "S", "chamber_id": 20, "importance": 0}, {"date": "2021-06-02", "action": "Read third time. Passed. (Ayes 36. Noes 0. Page 1375.) Ordered to the Assembly.", "chamber": "S", "chamber_id": 20, "importance": 1}, {"date": "2021-06-02", "action": "In Assembly. Read first time. Held at Desk.", "chamber": "A", "chamber_id": 19, "importance": 0}, {"date": "2021-06-10", "action": "Referred to Com. on NAT. RES.", "chamber": "A", "chamber_id": 19, "importance": 1}, {"date": "2021-07-12", "action": "From committee: Do pass as amended and re-refer to Com. on APPR. (Ayes 8. Noes 0.) (July 7).", "chamber": "A", "chamber_id": 19, "importance": 1}, {"date": "2021-07-13", "action": "Read second time and amended. Re-referred to Com. on APPR.", "chamber": "A", "chamber_id": 19, "importance": 1}, {"date": "2021-08-19", "action": "August 19 set for first hearing. Placed on suspense file.", "chamber": "A", "chamber_id": 19, "importance": 0}, {"date": "2021-08-26", "action": "From committee: Do pass as amended. (Ayes 12. Noes 0.) (August 26).", "chamber": "A", "chamber_id": 19, "importance": 1}, {"date": "2021-08-30", "action": "Read second time and amended. Ordered to second reading.", "chamber": "A", "chamber_id": 19, "importance": 0}, {"date": "2021-08-31", "action": "Read second time. Ordered to third reading.", "chamber": "A", "chamber_id": 19, "importance": 0}, {"date": "2021-09-10", "action": "Read third time. Passed. (Ayes 55. Noes 8. Page 3132.) Ordered to the Senate.", "chamber": "A", "chamber_id": 19, "importance": 0}, {"date": "2021-09-10", "action": "In Senate. Concurrence in Assembly amendments pending.", "chamber": "S", "chamber_id": 20, "importance": 0}, {"date": "2021-09-10", "action": "Assembly amendments concurred in. (Ayes 30. Noes 0. Page 2634.) Ordered to engrossing and enrolling.", "chamber": "S", "chamber_id": 20, "importance": 1}, {"date": "2021-09-17", "action": "Enrolled and presented to the Governor at 1:30 p.m.", "chamber": "", "chamber_id": 0, "importance": 0}, {"date": "2021-10-08", "action": "Approved by the Governor.", "chamber": "", "chamber_id": 0, "importance": 0}, {"date": "2021-10-08", "action": "Chaptered by Secretary of State. Chapter 727, Statutes of 2021.", "chamber": "", "chamber_id": 0, "importance": 1}], "sponsors": [{"people_id": 18070, "person_hash": "xjj237d8", "party_id": "1", "state_id": 5, "party": "D", "role_id": 2, "role": "Sen", "name": "Henry Stern", "first_name": "Henry", "middle_name": "", "last_name": "Stern", "suffix": "", "nickname": "", "district": "SD-027", "ftm_eid": 39707348, "votesmart_id": 169182, "opensecrets_id": "", "knowwho_pid": 392392, "ballotpedia": "Henry_Stern", "sponsor_type_id": 1, "sponsor_order": 1, "committee_sponsor": 0, "committee_id": 0, "state_federal": 0}, {"people_id": 22932, "person_hash": "34231s6y", "party_id": "1", "state_id": 5, "party": "D", "role_id": 1, "role": "Rep", "name": "Isaac Bryan", "first_name": "Isaac", "middle_name": "", "last_name": "Bryan", "suffix": "", "nickname": "", "district": "HD-054", "ftm_eid": 0, "votesmart_id": 195907, "opensecrets_id": "", "knowwho_pid": 722792, "ballotpedia": "Isaac_Bryan", "sponsor_type_id": 3, "sponsor_order": 2, "committee_sponsor": 0, "committee_id": 0, "state_federal": 0}], "sasts": [], "subjects": [], "texts": [{"doc_id": 2292510, "date": "2021-02-12", "type": "Introduced", "type_id": 1, "mime": "text/html", "mime_id": 1, "url": "https://legiscan.com/CA/text/SB406/id/2292510", "state_link": "https://leginfo.legislature.ca.gov/faces/billTextClient.xhtml?bill_id=202120220SB406#99INT", "text_size": 6117, "text_hash": "f4c06c53a3897a5d060ebe98ec8b43ac"}, {"doc_id": 2356734, "date": "2021-04-05", "type": "Amended", "type_id": 3, "mime": "text/html", "mime_id": 1, "url": "https://legiscan.com/CA/text/SB406/id/2356734", "state_link": "https://leginfo.legislature.ca.gov/faces/billTextClient.xhtml?bill_id=202120220SB406#98AMD", "text_size": 32337, "text_hash": "3bb203d847723e4c05a0de36a94ddf20"}, {"doc_id": 2401453, "date": "2021-05-20", "type": "Amended", "type_id": 3, "mime": "text/html", "mime_id": 1, "url": "https://legiscan.com/CA/text/SB406/id/2401453", "state_link": "https://leginfo.legislature.ca.gov/faces/billTextClient.xhtml?bill_id=202120220SB406#97AMD", "text_size": 24605, "text_hash": "079698ef8e6c99178dba537167e27348"}, {"doc_id": 2424462, "date": "2021-07-13", "type": "Amended", "type_id": 3, "mime": "text/html", "mime_id": 1, "url": "https://legiscan.com/CA/text/SB406/id/2424462", "state_link": "https://leginfo.legislature.ca.gov/faces/billTextClient.xhtml?bill_id=202120220SB406#96AMD", "text_size": 26379, "text_hash": "a26d8fcddd5346c74f4f25c07b951320"}, {"doc_id": 2430206, "date": "2021-08-30", "type": "Amended", "type_id": 3, "mime": "text/html", "mime_id": 1, "url": "https://legiscan.com/CA/text/SB406/id/2430206", "state_link": "https://leginfo.legislature.ca.gov/faces/billTextClient.xhtml?bill_id=202120220SB406#95AMD", "text_size": 29839, "text_hash": "5bfa30cbe82027fb1f50138ee0d41578"}, {"doc_id": 2433029, "date": "2021-09-14", "type": "Enrolled", "type_id": 5, "mime": "text/html", "mime_id": 1, "url": "https://legiscan.com/CA/text/SB406/id/2433029", "state_link": "https://leginfo.legislature.ca.gov/faces/billTextClient.xhtml?bill_id=202120220SB406#94ENR", "text_size": 27433, "text_hash": "e3fa71555ba9bcf3af77852484543acf"}, {"doc_id": 2436790, "date": "2021-10-08", "type": "Chaptered", "type_id": 6, "mime": "text/html", "mime_id": 1, "url": "https://legiscan.com/CA/text/SB406/id/2436790", "state_link": "https://leginfo.legislature.ca.gov/faces/billTextClient.xhtml?bill_id=202120220SB406#93CHP", "text_size": 25174, "text_hash": "61291acdf18f86a707aec70a7766918c"}], "votes": [{"roll_call_id": 1051924, "date": "2021-04-13", "desc": "Do pass, but first be re-referred to the Committee on [Appropriations]", "yea": 7, "nay": 0, "nv": 2, "absent": 0, "total": 9, "passed": 1, "chamber": "S", "chamber_id": 20, "url": "https://legiscan.com/CA/rollcall/SB406/id/1051924", "state_link": "http://leginfo.legislature.ca.gov/faces/billVotesClient.xhtml?bill_id=202120220SB406"}, {"roll_call_id": 1056367, "date": "2021-04-19", "desc": "Placed on suspense file", "yea": 7, "nay": 0, "nv": 0, "absent": 0, "total": 7, "passed": 1, "chamber": "S", "chamber_id": 20, "url": "https://legiscan.com/CA/rollcall/SB406/id/1056367", "state_link": "http://leginfo.legislature.ca.gov/faces/billVotesClient.xhtml?bill_id=202120220SB406"}, {"roll_call_id": 1081814, "date": "2021-05-20", "desc": "Do pass as amended", "yea": 6, "nay": 0, "nv": 1, "absent": 0, "total": 7, "passed": 1, "chamber": "S", "chamber_id": 20, "url": "https://legiscan.com/CA/rollcall/SB406/id/1081814", "state_link": "http://leginfo.legislature.ca.gov/faces/billVotesClient.xhtml?bill_id=202120220SB406"}, {"roll_call_id": 1090410, "date": "2021-06-02", "desc": "Senate 3rd Reading SB406 Stern", "yea": 36, "nay": 0, "nv": 4, "absent": 0, "total": 40, "passed": 1, "chamber": "S", "chamber_id": 20, "url": "https://legiscan.com/CA/rollcall/SB406/id/1090410", "state_link": "http://leginfo.legislature.ca.gov/faces/billVotesClient.xhtml?bill_id=202120220SB406"}, {"roll_call_id": 1104486, "date": "2021-07-07", "desc": "Do pass as amended and be re-referred to the Committee on [Appropriations]", "yea": 8, "nay": 0, "nv": 3, "absent": 0, "total": 11, "passed": 1, "chamber": "A", "chamber_id": 19, "url": "https://legiscan.com/CA/rollcall/SB406/id/1104486", "state_link": "http://leginfo.legislature.ca.gov/faces/billVotesClient.xhtml?bill_id=202120220SB406"}, {"roll_call_id": 1106995, "date": "2021-08-26", "desc": "Do pass as amended", "yea": 12, "nay": 0, "nv": 0, "absent": 4, "total": 16, "passed": 1, "chamber": "A", "chamber_id": 19, "url": "https://legiscan.com/CA/rollcall/SB406/id/1106995", "state_link": "http://leginfo.legislature.ca.gov/faces/billVotesClient.xhtml?bill_id=202120220SB406"}, {"roll_call_id": 1108663, "date": "2021-09-10", "desc": "Unfinished Business SB406 Stern et al. By Kamlager Concurrence", "yea": 30, "nay": 0, "nv": 0, "absent": 10, "total": 40, "passed": 1, "chamber": "S", "chamber_id": 20, "url": "https://legiscan.com/CA/rollcall/SB406/id/1108663", "state_link": "http://leginfo.legislature.ca.gov/faces/billVotesClient.xhtml?bill_id=202120220SB406"}, {"roll_call_id": 1108664, "date": "2021-09-10", "desc": "SB 406 Stern Senate Third Reading By Bryan", "yea": 55, "nay": 8, "nv": 0, "absent": 17, "total": 80, "passed": 1, "chamber": "A", "chamber_id": 19, "url": "https://legiscan.com/CA/rollcall/SB406/id/1108664", "state_link": "http://leginfo.legislature.ca.gov/faces/billVotesClient.xhtml?bill_id=202120220SB406"}], "amendments": [], "supplements": [], "calendar": [{"type_id": 1, "type": "Hearing", "date": "2021-04-13", "time": "09:00", "location": "John L. Burton Hearing Room", "description": "Senate Natural Resources and Water Hearing"}, {"type_id": 1, "type": "Hearing", "date": "2021-04-19", "time": "09:00", "location": "John L. Burton Hearing Room", "description": "Senate Appropriations Hearing"}, {"type_id": 1, "type": "Hearing", "date": "2021-05-20", "time": "00:00", "location": "Senate Chamber", "description": "Senate Appropriations Hearing"}, {"type_id": 1, "type": "Hearing", "date": "2021-07-07", "time": "09:00", "location": "State Capitol, Room 4202", "description": "Assembly Natural Resources Hearing"}, {"type_id": 1, "type": "Hearing", "date": "2021-08-19", "time": "00:00", "location": "State Capitol, Room 4202", "description": "Assembly Appropriations Hearing"}, {"type_id": 1, "type": "Hearing", "date": "2021-08-26", "time": "00:00", "location": "State Capitol, Room 4202", "description": "Assembly Appropriations Hearing"}]}}