{"status": "OK", "bill": {"bill_id": 367467, "change_hash": "4eefa876bd62e19ae11a5d4402286027", "session_id": 927, "session": {"session_id": 927, "state_id": 11, "year_start": 2012, "year_end": 2012, "prefile": 0, "sine_die": 1, "prior": 1, "special": 0, "session_tag": "Regular Session", "session_title": "2012 Regular Session", "session_name": "2012 Regular Session"}, "url": "https://legiscan.com/HI/bill/SB652/2012", "state_link": "http://www.capitol.hawaii.gov/measure_indiv.aspx?billtype=SB&billnumber=652", "completed": 0, "status": 2, "status_date": "2011-03-08", "progress": [{"date": "2011-01-21", "event": 1}, {"date": "2011-01-24", "event": 9}, {"date": "2011-02-16", "event": 10}, {"date": "2011-02-16", "event": 9}, {"date": "2011-03-04", "event": 10}, {"date": "2011-03-08", "event": 2}, {"date": "2011-03-10", "event": 9}, {"date": "2011-03-24", "event": 10}, {"date": "2011-03-24", "event": 9}, {"date": "2011-04-08", "event": 10}], "state": "HI", "state_id": 11, "bill_number": "SB652", "bill_type": "B", "bill_type_id": "1", "body": "S", "body_id": 32, "current_body": "S", "current_body_id": 32, "title": "Mortgage Foreclosures; Task Force", "description": "Implements recommendations of the Mortgage Foreclosure Task Force relating to service of notice, conversion from nonjudicial to judicial foreclosure, the bar against deficiency judgments, notice of pendency of action, and extinguishment of the mortgagor's interest. Requires 21-day notice of foreclosure. Requires public sale of property after a nonjudicial power of sale foreclosure to be held at the state building in the county seat of the county where the property is located or, for the City and County of Honolulu, at the state building designated by the Department of Accounting and General Services. Effective July 1, 2030. (SB652 HD1)", "pending_committee_id": 0, "committee": [], "referrals": [{"date": "2011-01-24", "committee_id": 2054, "chamber": "S", "chamber_id": 32, "name": "Commerce and Consumer Protection"}, {"date": "2011-02-16", "committee_id": 2065, "chamber": "S", "chamber_id": 32, "name": "Ways and Means"}], "history": [{"date": "2011-01-21", "action": "(S) Introduced.", "chamber": "", "chamber_id": 0, "importance": 1}, {"date": "2011-01-24", "action": "(S) Passed First Reading.", "chamber": "", "chamber_id": 0, "importance": 0}, {"date": "2011-01-24", "action": "(S) Referred to CPN, WAM.", "chamber": "", "chamber_id": 0, "importance": 1}, {"date": "2011-01-27", "action": "(S) The committee(s) on CPN has scheduled a public hearing on 02-02-11 8:30AM in conference room 229.", "chamber": "", "chamber_id": 0, "importance": 0}, {"date": "2011-02-02", "action": "(S) The committee(s) on CPN deferred the measure until 02-04-11 10:00AM in conference room 229.", "chamber": "", "chamber_id": 0, "importance": 0}, {"date": "2011-02-04", "action": "(S) The committee(s) on CPN recommend(s) that the measure be PASSED, WITH AMENDMENTS. The votes in CPN were as follows: 6 Aye(s): Senator(s) Baker, Taniguchi, Galuteria, Green, Nishihara, Solomon; Aye(s) with reservations: none ; 0 No(es): none; and 1 Excused: Senator(s) Slom.", "chamber": "", "chamber_id": 0, "importance": 0}, {"date": "2011-02-16", "action": "(S) Reported from CPN (Stand. Com. Rep. No. 266) with recommendation of passage on Second Reading, as amended (SD 1) and referral to WAM.", "chamber": "", "chamber_id": 0, "importance": 1}, {"date": "2011-02-16", "action": "(S) Report adopted; Passed Second Reading, as amended (SD 1) and referred to WAM.", "chamber": "", "chamber_id": 0, "importance": 1}, {"date": "2011-02-22", "action": "(S) The committee(s) on WAM will hold a public decision making on 02-24-11 9:00AM in conference room 211.", "chamber": "", "chamber_id": 0, "importance": 0}, {"date": "2011-02-24", "action": "(S) The committee(s) on WAM recommend(s) that the measure be PASSED, WITH AMENDMENTS. The votes in WAM were as follows: 13 Aye(s): Senator(s) Ige, Chun Oakland, Dela Cruz, English, Espero, Fukunaga, Kahele, Kim, Kouchi, Ryan, Tokuda, Wakai, Slom; Aye(s) with reservations: none ; 0 No(es): none; and 1 Excused: Senator(s) Kidani.", "chamber": "", "chamber_id": 0, "importance": 0}, {"date": "2011-03-04", "action": "(S) Reported from WAM (Stand. Com. Rep. No. 606) with recommendation of passage on Third Reading, as amended (SD 2).", "chamber": "", "chamber_id": 0, "importance": 1}, {"date": "2011-03-04", "action": "(S) 48 Hrs. Notice 03-08-11.", "chamber": "", "chamber_id": 0, "importance": 0}, {"date": "2011-03-08", "action": "(S) Report adopted; Passed Third Reading, as amended (SD 2). Ayes, 25; Aye(s) with reservations: none . Noes, 0 (none). Excused, 0 (none). Transmitted to House.", "chamber": "", "chamber_id": 0, "importance": 1}, {"date": "2011-03-08", "action": "(H) Received from Senate (Sen. Com. No. 148) in amended form (SD 2).", "chamber": "", "chamber_id": 0, "importance": 0}, {"date": "2011-03-10", "action": "(H) Pass First Reading", "chamber": "", "chamber_id": 0, "importance": 0}, {"date": "2011-03-10", "action": "(H) Referred to CPC/JUD, FIN, referral sheet 33", "chamber": "", "chamber_id": 0, "importance": 1}, {"date": "2011-03-10", "action": "(H) Bill scheduled to be heard by CPC/JUD on Wednesday, 03-16-11 2:00PM in House conference room 325.", "chamber": "", "chamber_id": 0, "importance": 0}, {"date": "2011-03-16", "action": "(H) The committee(s) recommends that the measure be deferred until 03-23-11.", "chamber": "", "chamber_id": 0, "importance": 0}, {"date": "2011-03-21", "action": "(H) Bill scheduled for decision making on Wednesday, 03-23-11 2:00PM in conference room 325.", "chamber": "", "chamber_id": 0, "importance": 0}, {"date": "2011-03-23", "action": "(H) The committees on CPC recommend that the measure be PASSED, UNAMENDED. The votes were as follows: 11 Ayes: Representative(s) Herkes, Yamane, Brower, Cabanilla, Keith-Agaran, Luke, B. Oshiro, Souki, Tsuji, Marumoto, Thielen; Ayes with reservations: none; Noes: none; and 4 Excused: Representative(s) Carroll, Ito, McKelvey, Ching.", "chamber": "", "chamber_id": 0, "importance": 0}, {"date": "2011-03-23", "action": "(H) The committees on JUD recommend that the measure be PASSED, UNAMENDED. The votes were as follows: 12 Ayes: Representative(s) Keith-Agaran, Rhoads, Brower, Cabanilla, Herkes, Luke, B. Oshiro, Souki, Tsuji, Fontaine, Marumoto, Thielen; Ayes with reservations: none; Noes: none; and 3 Excused: Representative(s) Carroll, Ito, McKelvey.", "chamber": "", "chamber_id": 0, "importance": 0}, {"date": "2011-03-24", "action": "(H) Reported from CPC/JUD (Stand. Com. Rep. No. 1208), recommending passage on Second Reading and referral to FIN.", "chamber": "", "chamber_id": 0, "importance": 1}, {"date": "2011-03-24", "action": "(H) Passed Second Reading and referred to the committee(s) on FIN with none voting no (0) and Har, Riviere, Wooley excused (3).", "chamber": "", "chamber_id": 0, "importance": 1}, {"date": "2011-03-30", "action": "(H) Bill scheduled to be heard by FIN on Friday, 04-01-11 5:00PM in House conference room 308.", "chamber": "", "chamber_id": 0, "importance": 0}, {"date": "2011-04-01", "action": "(H) The committees on FIN recommend that the measure be PASSED, WITH AMENDMENTS. The votes were as follows: 16 Ayes: Representative(s) M. Oshiro, M. Lee, Chong, Choy, Coffman, Cullen, Har, Hashem, Ichiyama, Jordan, C. Lee, Morikawa, Yamashita, Marumoto, Riviere, Ward; Ayes with reservations: none; Noes: none; and 1 Excused: Representative(s) Tokioka.", "chamber": "", "chamber_id": 0, "importance": 0}, {"date": "2011-04-08", "action": "(H) Reported from FIN (Stand. Com. Rep. No. 1511) as amended in HD 1, recommending passage on Third Reading.", "chamber": "", "chamber_id": 0, "importance": 1}, {"date": "2011-04-08", "action": "(H) Forty-eight (48) hours notice Tuesday, 04-12-11.", "chamber": "", "chamber_id": 0, "importance": 0}, {"date": "2011-04-12", "action": "(H) Passed Third Reading as amended in HD 1 with none voting aye with reservations; none voting no (0) and Representative(s) Kawakami excused (1). Transmitted to Senate.", "chamber": "", "chamber_id": 0, "importance": 0}, {"date": "2011-04-14", "action": "(S) Received from House (Hse. Com. No. 455).", "chamber": "", "chamber_id": 0, "importance": 0}, {"date": "2011-04-14", "action": "(S) Senate disagrees with House amendments.", "chamber": "", "chamber_id": 0, "importance": 0}, {"date": "2011-04-14", "action": "(H) Received notice of disagreement (Sen. Com. No. 605).", "chamber": "", "chamber_id": 0, "importance": 0}, {"date": "2011-04-18", "action": "(S) Senate Conferees appointed: Baker, Chair; Ige, Co-Chair(s); Slom.", "chamber": "", "chamber_id": 0, "importance": 0}, {"date": "2011-04-18", "action": "(H) House conferees appointed: Herkes, Keith-Agaran, M. Oshiro Co-Chairs; Cabanilla, Ito, McKelvey, Riviere.", "chamber": "", "chamber_id": 0, "importance": 0}, {"date": "2011-04-18", "action": "(H) Received notice of Senate conferees (Sen. Com. No. 643).", "chamber": "", "chamber_id": 0, "importance": 0}, {"date": "2011-04-18", "action": "(S) Conference committee meeting scheduled for 04-20-11 9:30AM in conference room 016.", "chamber": "", "chamber_id": 0, "importance": 0}, {"date": "2011-04-19", "action": "(S) Received notice of appointment of House conferees (Hse. Com. No. 652).", "chamber": "", "chamber_id": 0, "importance": 0}, {"date": "2011-12-01", "action": "Carried over to 2012 Regular Session.", "chamber": "", "chamber_id": 0, "importance": 0}, {"date": "2012-04-12", "action": "(H) House Conferee(s) discharged.", "chamber": "", "chamber_id": 0, "importance": 0}, {"date": "2012-04-13", "action": "(S) Received notice of discharge of conferees (Hse. Com. No. 548).", "chamber": "", "chamber_id": 0, "importance": 0}, {"date": "2012-04-13", "action": "(S) Senate Conferee(s) discharged.", "chamber": "", "chamber_id": 0, "importance": 0}, {"date": "2012-04-13", "action": "(H) Received notice of all Senate conferees being discharged (Sen. Com. No. 747).", "chamber": "", "chamber_id": 0, "importance": 0}], "sponsors": [{"people_id": 8424, "person_hash": "vn68evmd", "party_id": "1", "state_id": 11, "party": "D", "role_id": 2, "role": "Sen", "name": "Brian Taniguchi", "first_name": "Brian", "middle_name": "T.", "last_name": "Taniguchi", "suffix": "", "nickname": "", "district": "SD-011", "ftm_eid": 13011589, "votesmart_id": 3416, "opensecrets_id": "", "knowwho_pid": 193902, "ballotpedia": "Brian_Taniguchi", "sponsor_type_id": 0, "sponsor_order": 0, "committee_sponsor": 0, "committee_id": 0, "state_federal": 0}, {"people_id": 8426, "person_hash": "6egtq387", "party_id": "1", "state_id": 11, "party": "D", "role_id": 2, "role": "Sen", "name": "Rosalyn Baker", "first_name": "Rosalyn", "middle_name": "H.", "last_name": "Baker", "suffix": "", "nickname": "", "district": "SD-006", "ftm_eid": 4105485, "votesmart_id": 3401, "opensecrets_id": "", "knowwho_pid": 211933, "ballotpedia": "Rosalyn_Baker", "sponsor_type_id": 0, "sponsor_order": 0, "committee_sponsor": 0, "committee_id": 0, "state_federal": 0}, {"people_id": 8428, "person_hash": "4fqd3ehr", "party_id": "1", "state_id": 11, "party": "D", "role_id": 2, "role": "Sen", "name": "William Espero", "first_name": "William", "middle_name": "C.", "last_name": "Espero", "suffix": "", "nickname": "Will", "district": "SD-019", "ftm_eid": 6397289, "votesmart_id": 1757, "opensecrets_id": "", "knowwho_pid": 193884, "ballotpedia": "William_Espero", "sponsor_type_id": 0, "sponsor_order": 0, "committee_sponsor": 0, "committee_id": 0, "state_federal": 0}, {"people_id": 8430, "person_hash": "tkrl1fcs", "party_id": "1", "state_id": 11, "party": "D", "role_id": 2, "role": "Sen", "name": "Shan Tsutsui", "first_name": "Shan", "middle_name": "S.", "last_name": "Tsutsui", "suffix": "", "nickname": "", "district": "SD-005", "ftm_eid": 13011583, "votesmart_id": 32228, "opensecrets_id": "", "knowwho_pid": 213999, "ballotpedia": "Shan_Tsutsui", "sponsor_type_id": 0, "sponsor_order": 0, "committee_sponsor": 0, "committee_id": 0, "state_federal": 0}, {"people_id": 8432, "person_hash": "p6yfe9gc", "party_id": "1", "state_id": 11, "party": "D", "role_id": 2, "role": "Sen", "name": "Josh Green", "first_name": "Josh", "middle_name": "", "last_name": "Green", "suffix": "", "nickname": "", "district": "SD-003", "ftm_eid": 6461769, "votesmart_id": 32389, "opensecrets_id": "", "knowwho_pid": 227425, "ballotpedia": "Joshua_Green", "sponsor_type_id": 0, "sponsor_order": 0, "committee_sponsor": 0, "committee_id": 0, "state_federal": 0}, {"people_id": 8434, "person_hash": "xytd9pz5", "party_id": "1", "state_id": 11, "party": "D", "role_id": 2, "role": "Sen", "name": "David Ige", "first_name": "David", "middle_name": "Y.", "last_name": "Ige", "suffix": "", "nickname": "", "district": "SD-016", "ftm_eid": 6401125, "votesmart_id": 3406, "opensecrets_id": "", "knowwho_pid": 193908, "ballotpedia": "David_Ige", "sponsor_type_id": 0, "sponsor_order": 0, "committee_sponsor": 0, "committee_id": 0, "state_federal": 0}, {"people_id": 8435, "person_hash": "0k90b1b1", "party_id": "1", "state_id": 11, "party": "D", "role_id": 2, "role": "Sen", "name": "Les Ihara", "first_name": "Les", "middle_name": "S.", "last_name": "Ihara", "suffix": "Jr.", "nickname": "", "district": "SD-010", "ftm_eid": 13011588, "votesmart_id": 3392, "opensecrets_id": "", "knowwho_pid": 193901, "ballotpedia": "Les_Ihara_Jr.", "sponsor_type_id": 0, "sponsor_order": 0, "committee_sponsor": 0, "committee_id": 0, "state_federal": 0}, {"people_id": 8437, "person_hash": "yhcmf4zx", "party_id": "1", "state_id": 11, "party": "D", "role_id": 2, "role": "Sen", "name": "Suzanne Chun Oakland", "first_name": "Suzanne", "middle_name": "N J", "last_name": "Chun Oakland", "suffix": "", "nickname": "", "district": "SD-013", "ftm_eid": 6397015, "votesmart_id": 3423, "opensecrets_id": "", "knowwho_pid": 193905, "ballotpedia": "Suzanne_Chun_Oakland", "sponsor_type_id": 0, "sponsor_order": 0, "committee_sponsor": 0, "committee_id": 0, "state_federal": 0}, {"people_id": 11379, "person_hash": "0dumi2hl", "party_id": "1", "state_id": 11, "party": "D", "role_id": 2, "role": "Sen", "name": "Malama Solomon", "first_name": "Malama", "middle_name": "", "last_name": "Solomon", "suffix": "", "nickname": "", "district": "SD-004", "ftm_eid": 6418139, "votesmart_id": 3413, "opensecrets_id": "", "knowwho_pid": 328318, "ballotpedia": "Malama_Solomon", "sponsor_type_id": 0, "sponsor_order": 0, "committee_sponsor": 0, "committee_id": 0, "state_federal": 0}], "sasts": [], "subjects": [], "texts": [{"doc_id": 536554, "date": "2011-01-22", "type": "Introduced", "type_id": 1, "mime": "text/html", "mime_id": 1, "url": "https://legiscan.com/HI/text/SB652/id/536554", "state_link": "http://www.capitol.hawaii.gov/session2012/Bills/SB652_.HTM", "text_size": 41611, "text_hash": "2c9a66e311bd92dc8262f03966ff25a0"}, {"doc_id": 536555, "date": "2011-04-09", "type": "Amended", "type_id": 3, "mime": "text/html", "mime_id": 1, "url": "https://legiscan.com/HI/text/SB652/id/536555", "state_link": "http://www.capitol.hawaii.gov/session2012/Bills/SB652_HD1_.HTM", "text_size": 46053, "text_hash": "dac8355a121d10a2cf45f548d405297d"}, {"doc_id": 536556, "date": "2011-02-16", "type": "Amended", "type_id": 3, "mime": "text/html", "mime_id": 1, "url": "https://legiscan.com/HI/text/SB652/id/536556", "state_link": "http://www.capitol.hawaii.gov/session2012/Bills/SB652_SD1_.HTM", "text_size": 46421, "text_hash": "9e77d1a17fbe952a10347192f625bee8"}, {"doc_id": 536557, "date": "2011-03-03", "type": "Amended", "type_id": 3, "mime": "text/html", "mime_id": 1, "url": "https://legiscan.com/HI/text/SB652/id/536557", "state_link": "http://www.capitol.hawaii.gov/session2012/Bills/SB652_SD2_.HTM", "text_size": 46063, "text_hash": "cd244f5c962723ec075c6bd4b5ebc8d3"}, {"doc_id": 536558, "date": "2011-04-09", "type": "Amended", "type_id": 3, "mime": "text/html", "mime_id": 1, "url": "https://legiscan.com/HI/text/SB652/id/536558", "state_link": "http://www.capitol.hawaii.gov/session2012/CommReports/SB652_HD1_HSCR1511_.HTM", "text_size": 8553, "text_hash": "2f6a36a3455151468c2be0c36a0ac6a9"}, {"doc_id": 536559, "date": "2011-02-16", "type": "Amended", "type_id": 3, "mime": "text/html", "mime_id": 1, "url": "https://legiscan.com/HI/text/SB652/id/536559", "state_link": "http://www.capitol.hawaii.gov/session2012/CommReports/SB652_SD1_SSCR266_.HTM", "text_size": 10032, "text_hash": "fa48183217c6b00faa40cf8e5db21e34"}, {"doc_id": 536560, "date": "2011-03-24", "type": "Amended", "type_id": 3, "mime": "text/html", "mime_id": 1, "url": "https://legiscan.com/HI/text/SB652/id/536560", "state_link": "http://www.capitol.hawaii.gov/session2012/CommReports/SB652_SD2_HSCR1208_.HTM", "text_size": 9043, "text_hash": "33cb808fe00669f77ae16a7812ef683d"}, {"doc_id": 536561, "date": "2011-03-03", "type": "Amended", "type_id": 3, "mime": "text/html", "mime_id": 1, "url": "https://legiscan.com/HI/text/SB652/id/536561", "state_link": "http://www.capitol.hawaii.gov/session2012/CommReports/SB652_SD2_SSCR606_.HTM", "text_size": 8450, "text_hash": "7731f3ea961c0056d8a449bfdb182fdf"}], "votes": [], "amendments": [], "supplements": [], "calendar": []}}