{"status": "OK", "bill": {"bill_id": 624766, "change_hash": "d25f37ff65fb5eda3092cac332e3cd3f", "session_id": 993, "session": {"session_id": 993, "state_id": 5, "year_start": 2013, "year_end": 2014, "prefile": 0, "sine_die": 1, "prior": 1, "special": 0, "session_tag": "Regular Session", "session_title": "2013-2014 Regular Session", "session_name": "2013-2014 Session"}, "url": "https://legiscan.com/CA/bill/SB1161/2013", "state_link": "http://www.leginfo.ca.gov/cgi-bin/postquery?bill_number=sb_1161&sess=1314&house=S", "completed": 1, "status": 4, "status_date": "2014-09-19", "progress": [{"date": "2014-02-20", "event": 1}, {"date": "2014-03-06", "event": 9}, {"date": "2014-04-02", "event": 9}, {"date": "2014-04-10", "event": 9}, {"date": "2014-04-28", "event": 10}, {"date": "2014-04-29", "event": 9}, {"date": "2014-05-23", "event": 10}, {"date": "2014-05-27", "event": 2}, {"date": "2014-06-02", "event": 9}, {"date": "2014-06-18", "event": 10}, {"date": "2014-06-18", "event": 9}, {"date": "2014-07-02", "event": 9}, {"date": "2014-08-14", "event": 10}, {"date": "2014-08-28", "event": 3}, {"date": "2014-09-19", "event": 8}, {"date": "2014-09-19", "event": 4}], "state": "CA", "state_id": 5, "bill_number": "SB1161", "bill_type": "B", "bill_type_id": "1", "body": "S", "body_id": 20, "current_body": "S", "current_body_id": 20, "title": "Drug Medi-Cal.", "description": "An act to add Section 14124.29 to the Welfare and Institutions Code, relating to Medi-Cal.", "pending_committee_id": 0, "committee": [], "referrals": [{"date": "2014-02-20", "committee_id": 489, "chamber": "S", "chamber_id": 20, "name": "Rules"}, {"date": "2014-04-10", "committee_id": 480, "chamber": "S", "chamber_id": 20, "name": "Health"}, {"date": "2014-04-28", "committee_id": 475, "chamber": "S", "chamber_id": 20, "name": "Appropriations"}, {"date": "2014-06-02", "committee_id": 457, "chamber": "A", "chamber_id": 19, "name": "Health"}, {"date": "2014-06-18", "committee_id": 449, "chamber": "A", "chamber_id": 19, "name": "Appropriations"}], "history": [{"date": "2014-02-20", "action": "Introduced. Read first time. To Com. on RLS. for assignment. To print. ", "chamber": "S", "chamber_id": 20, "importance": 1}, {"date": "2014-02-21", "action": "From printer. May be acted upon on or after March 23.", "chamber": "S", "chamber_id": 20, "importance": 0}, {"date": "2014-03-06", "action": "Referred to Com. on RLS.", "chamber": "S", "chamber_id": 20, "importance": 1}, {"date": "2014-04-02", "action": "From committee with author's amendments. Read second time and amended. Re-referred to Com. on RLS.", "chamber": "S", "chamber_id": 20, "importance": 1}, {"date": "2014-04-10", "action": "Re-referred to Com. on HEALTH. From committee with author's amendments. Read second time and amended. Re-referred to Com. on HEALTH.", "chamber": "S", "chamber_id": 20, "importance": 1}, {"date": "2014-04-11", "action": "Set for hearing April 24.", "chamber": "S", "chamber_id": 20, "importance": 0}, {"date": "2014-04-28", "action": "From committee: Do pass as amended and re-refer to Com. on APPR. (Ayes 7. Noes 0. Page 3280.) (April 24).", "chamber": "S", "chamber_id": 20, "importance": 1}, {"date": "2014-04-29", "action": "Read second time and amended. Re-referred to Com. on APPR.", "chamber": "S", "chamber_id": 20, "importance": 1}, {"date": "2014-05-02", "action": "Set for hearing May 12.", "chamber": "S", "chamber_id": 20, "importance": 0}, {"date": "2014-05-12", "action": "Placed on APPR. suspense file.", "chamber": "S", "chamber_id": 20, "importance": 0}, {"date": "2014-05-16", "action": "Set for hearing May 23.", "chamber": "S", "chamber_id": 20, "importance": 0}, {"date": "2014-05-23", "action": "From committee: Do pass. (Ayes 6. Noes 1. Page 3710.) (May 23). Read second time. Ordered to third reading.", "chamber": "S", "chamber_id": 20, "importance": 1}, {"date": "2014-05-27", "action": "Read third time. Passed. (Ayes 32. Noes 4. Page 3602.) Ordered to the Assembly.", "chamber": "S", "chamber_id": 20, "importance": 1}, {"date": "2014-05-28", "action": "In Assembly. Read first time. Held at Desk.", "chamber": "A", "chamber_id": 19, "importance": 0}, {"date": "2014-06-02", "action": "Referred to Com. on HEALTH.", "chamber": "A", "chamber_id": 19, "importance": 1}, {"date": "2014-06-18", "action": "From committee: Do pass and re-refer to Com. on APPR. (Ayes 17. Noes 0.) (June 17). Re-referred to Com. on APPR.", "chamber": "A", "chamber_id": 19, "importance": 1}, {"date": "2014-07-02", "action": "Set, first hearing. Referred to APPR. suspense file.", "chamber": "A", "chamber_id": 19, "importance": 1}, {"date": "2014-08-14", "action": "From committee: Do pass as amended. (Ayes 16. Noes 1.) (August 14).", "chamber": "A", "chamber_id": 19, "importance": 1}, {"date": "2014-08-18", "action": "Read second time and amended. Ordered to second reading.", "chamber": "A", "chamber_id": 19, "importance": 0}, {"date": "2014-08-19", "action": "Read second time. Ordered to third reading.", "chamber": "A", "chamber_id": 19, "importance": 0}, {"date": "2014-08-22", "action": "Read third time and amended. (Page 6343.) Ordered to third reading.", "chamber": "A", "chamber_id": 19, "importance": 0}, {"date": "2014-08-27", "action": "Read third time. Passed. (Ayes 76. Noes 1. Page 6543.) Ordered to the Senate.", "chamber": "A", "chamber_id": 19, "importance": 0}, {"date": "2014-08-27", "action": "In Senate. Concurrence in Assembly amendments pending.", "chamber": "S", "chamber_id": 20, "importance": 0}, {"date": "2014-08-28", "action": "Assembly amendments concurred in. (Ayes 34. Noes 0. Page 4944.) Ordered to engrossing and enrolling.", "chamber": "S", "chamber_id": 20, "importance": 1}, {"date": "2014-09-04", "action": "Enrolled and presented to the Governor at 2 p.m.", "chamber": "S", "chamber_id": 20, "importance": 0}, {"date": "2014-09-19", "action": "Approved by the Governor.", "chamber": "", "chamber_id": 0, "importance": 0}, {"date": "2014-09-19", "action": "Chaptered by Secretary of State. Chapter 486, Statutes of 2014.", "chamber": "", "chamber_id": 0, "importance": 1}], "sponsors": [{"people_id": 1498, "person_hash": "t93gy978", "party_id": "1", "state_id": 5, "party": "D", "role_id": 2, "role": "Sen", "name": "Jim Beall", "first_name": "Jim", "middle_name": "", "last_name": "Beall", "suffix": "Jr.", "nickname": "", "district": "SD-015", "ftm_eid": 776647, "votesmart_id": 58229, "opensecrets_id": "", "knowwho_pid": 248442, "ballotpedia": "James_Beall_Jr.", "sponsor_type_id": 1, "sponsor_order": 1, "committee_sponsor": 0, "committee_id": 0, "state_federal": 0}, {"people_id": 16094, "person_hash": "m68q8yjl", "party_id": "1", "state_id": 5, "party": "D", "role_id": 1, "role": "Rep", "name": "Matt Dababneh", "first_name": "Matt", "middle_name": "", "last_name": "Dababneh", "suffix": "", "nickname": "", "district": "HD-045", "ftm_eid": 18912256, "votesmart_id": 144893, "opensecrets_id": "", "knowwho_pid": 242136, "ballotpedia": "Matt_Dababneh", "sponsor_type_id": 3, "sponsor_order": 2, "committee_sponsor": 0, "committee_id": 0, "state_federal": 0}], "sasts": [], "subjects": [], "texts": [{"doc_id": 965584, "date": "2014-02-20", "type": "Introduced", "type_id": 1, "mime": "text/html", "mime_id": 1, "url": "https://legiscan.com/CA/text/SB1161/id/965584", "state_link": "http://www.leginfo.ca.gov/pub/13-14/bill/sen/sb_1151-1200/sb_1161_bill_20140220_introduced.html", "text_size": 4287, "text_hash": "897002b865ed046b0e14dd39271f90dc"}, {"doc_id": 1004231, "date": "2014-04-02", "type": "Amended", "type_id": 3, "mime": "text/html", "mime_id": 1, "url": "https://legiscan.com/CA/text/SB1161/id/1004231", "state_link": "http://www.leginfo.ca.gov/pub/13-14/bill/sen/sb_1151-1200/sb_1161_bill_20140402_amended_sen_v98.html", "text_size": 9866, "text_hash": "b6186945568d7a9e6d71856084b47620"}, {"doc_id": 1009011, "date": "2014-04-10", "type": "Amended", "type_id": 3, "mime": "text/html", "mime_id": 1, "url": "https://legiscan.com/CA/text/SB1161/id/1009011", "state_link": "http://www.leginfo.ca.gov/pub/13-14/bill/sen/sb_1151-1200/sb_1161_bill_20140410_amended_sen_v97.html", "text_size": 5769, "text_hash": "5e852b90bd4830dd2469c74d56fc9874"}, {"doc_id": 1016742, "date": "2014-04-29", "type": "Amended", "type_id": 3, "mime": "text/html", "mime_id": 1, "url": "https://legiscan.com/CA/text/SB1161/id/1016742", "state_link": "http://www.leginfo.ca.gov/pub/13-14/bill/sen/sb_1151-1200/sb_1161_bill_20140429_amended_sen_v96.html", "text_size": 6150, "text_hash": "834b686cea6d1271673fcc8d97973ce8"}, {"doc_id": 1042689, "date": "2014-08-18", "type": "Amended", "type_id": 3, "mime": "text/html", "mime_id": 1, "url": "https://legiscan.com/CA/text/SB1161/id/1042689", "state_link": "http://www.leginfo.ca.gov/pub/13-14/bill/sen/sb_1151-1200/sb_1161_bill_20140818_amended_asm_v95.html", "text_size": 6568, "text_hash": "22ac9438c96b99949a0c022143945425"}, {"doc_id": 1043506, "date": "2014-08-22", "type": "Amended", "type_id": 3, "mime": "text/html", "mime_id": 1, "url": "https://legiscan.com/CA/text/SB1161/id/1043506", "state_link": "http://www.leginfo.ca.gov/pub/13-14/bill/sen/sb_1151-1200/sb_1161_bill_20140822_amended_asm_v94.html", "text_size": 6242, "text_hash": "ff252def5f902cca98f9194acce6a81c"}, {"doc_id": 1044322, "date": "2014-09-02", "type": "Enrolled", "type_id": 5, "mime": "text/html", "mime_id": 1, "url": "https://legiscan.com/CA/text/SB1161/id/1044322", "state_link": "http://www.leginfo.ca.gov/pub/13-14/bill/sen/sb_1151-1200/sb_1161_bill_20140902_enrolled.html", "text_size": 5092, "text_hash": "7d51d1d74ff97071393c6f6fba73a9b7"}, {"doc_id": 1046143, "date": "2014-09-19", "type": "Chaptered", "type_id": 6, "mime": "text/html", "mime_id": 1, "url": "https://legiscan.com/CA/text/SB1161/id/1046143", "state_link": "http://www.leginfo.ca.gov/pub/13-14/bill/sen/sb_1151-1200/sb_1161_bill_20140919_chaptered.html", "text_size": 5200, "text_hash": "6a65e5d8ca22c0a9e639d53859f10194"}], "votes": [{"roll_call_id": 359867, "date": "2014-04-24", "desc": "Do pass as amended, and re-refer to the Committee on \tAppropriations", "yea": 7, "nay": 0, "nv": 2, "absent": 0, "total": 9, "passed": 1, "chamber": "S", "chamber_id": 20, "url": "https://legiscan.com/CA/rollcall/SB1161/id/359867", "state_link": "http://www.leginfo.ca.gov/pub/13-14/bill/sen/sb_1151-1200/sb_1161_vote_20140424_000002_sen_comm.html"}, {"roll_call_id": 363729, "date": "2014-05-12", "desc": "Placed on Appropriations Suspense file", "yea": 7, "nay": 0, "nv": 0, "absent": 0, "total": 7, "passed": 1, "chamber": "S", "chamber_id": 20, "url": "https://legiscan.com/CA/rollcall/SB1161/id/363729", "state_link": "http://www.leginfo.ca.gov/pub/13-14/bill/sen/sb_1151-1200/sb_1161_vote_20140512_000001_sen_comm.html"}, {"roll_call_id": 366781, "date": "2014-05-23", "desc": "Do pass", "yea": 6, "nay": 1, "nv": 0, "absent": 0, "total": 7, "passed": 1, "chamber": "S", "chamber_id": 20, "url": "https://legiscan.com/CA/rollcall/SB1161/id/366781", "state_link": "http://www.leginfo.ca.gov/pub/13-14/bill/sen/sb_1151-1200/sb_1161_vote_20140523_000002_sen_comm.html"}, {"roll_call_id": 367554, "date": "2014-05-27", "desc": "Senate 3rd Reading SB1161 Beall", "yea": 32, "nay": 4, "nv": 4, "absent": 0, "total": 40, "passed": 1, "chamber": "S", "chamber_id": 20, "url": "https://legiscan.com/CA/rollcall/SB1161/id/367554", "state_link": "http://www.leginfo.ca.gov/pub/13-14/bill/sen/sb_1151-1200/sb_1161_vote_20140527_0304PM_sen_floor.html"}, {"roll_call_id": 372205, "date": "2014-06-17", "desc": "Do pass and be re-referred to the Committee on Appropriations", "yea": 17, "nay": 0, "nv": 0, "absent": 2, "total": 19, "passed": 1, "chamber": "A", "chamber_id": 19, "url": "https://legiscan.com/CA/rollcall/SB1161/id/372205", "state_link": "http://www.leginfo.ca.gov/pub/13-14/bill/sen/sb_1151-1200/sb_1161_vote_20140617_000001_asm_comm.html"}, {"roll_call_id": 377540, "date": "2014-08-14", "desc": "Do pass as amended", "yea": 16, "nay": 1, "nv": 0, "absent": 0, "total": 17, "passed": 1, "chamber": "A", "chamber_id": 19, "url": "https://legiscan.com/CA/rollcall/SB1161/id/377540", "state_link": "http://www.leginfo.ca.gov/pub/13-14/bill/sen/sb_1151-1200/sb_1161_vote_20140814_000002_asm_comm.html"}, {"roll_call_id": 378791, "date": "2014-08-27", "desc": "SB 1161 Beall  Senate Third Reading  By CHESBRO", "yea": 76, "nay": 1, "nv": 0, "absent": 2, "total": 79, "passed": 1, "chamber": "A", "chamber_id": 19, "url": "https://legiscan.com/CA/rollcall/SB1161/id/378791", "state_link": "http://www.leginfo.ca.gov/pub/13-14/bill/sen/sb_1151-1200/sb_1161_vote_20140827_1133AM_asm_floor.html"}, {"roll_call_id": 378959, "date": "2014-08-28", "desc": "Unfinished Business SB1161 Beall Concurrence", "yea": 34, "nay": 0, "nv": 6, "absent": 0, "total": 40, "passed": 1, "chamber": "S", "chamber_id": 20, "url": "https://legiscan.com/CA/rollcall/SB1161/id/378959", "state_link": "http://www.leginfo.ca.gov/pub/13-14/bill/sen/sb_1151-1200/sb_1161_vote_20140828_0502PM_sen_floor.html"}], "amendments": [], "supplements": [], "calendar": []}}