{"status": "OK", "bill": {"bill_id": 1421827, "change_hash": "334aeeb573e300e4b2b6ea27aaabf9bb", "session_id": 1799, "session": {"session_id": 1799, "state_id": 11, "year_start": 2021, "year_end": 2021, "prefile": 0, "sine_die": 1, "prior": 1, "special": 0, "session_tag": "Regular Session", "session_title": "2021 Regular Session", "session_name": "2021 Regular Session"}, "url": "https://legiscan.com/HI/bill/HB718/2021", "state_link": "http://www.capitol.hawaii.gov/measure_indiv.aspx?billtype=HB&billnumber=718&year=2021", "completed": 0, "status": 2, "status_date": "2021-03-05", "progress": [{"date": "2021-01-27", "event": 1}, {"date": "2021-01-27", "event": 9}, {"date": "2021-02-10", "event": 10}, {"date": "2021-02-10", "event": 9}, {"date": "2021-02-19", "event": 10}, {"date": "2021-02-19", "event": 9}, {"date": "2021-03-05", "event": 10}, {"date": "2021-03-05", "event": 2}, {"date": "2021-03-09", "event": 9}, {"date": "2021-03-25", "event": 10}, {"date": "2021-03-25", "event": 9}], "state": "HI", "state_id": 11, "bill_number": "HB718", "bill_type": "B", "bill_type_id": "1", "body": "H", "body_id": 31, "current_body": "S", "current_body_id": 32, "title": "Relating To Health.", "description": "Requires the department of human services to compile information regarding employers having employees who receive public assistance and to submit a report to the legislature on the 50 employers with the highest number of employees receiving public assistance. Requires the department of labor and industrial relations to share employment data with the department of human services. Effective 7/1/2060. (SD1)", "pending_committee_id": 3756, "committee": {"committee_id": 3756, "chamber": "S", "chamber_id": 32, "name": "Judiciary"}, "referrals": [{"date": "2021-01-27", "committee_id": 4405, "chamber": "H", "chamber_id": 31, "name": "Health, Human Services, & Homelessness"}, {"date": "2021-02-10", "committee_id": 2034, "chamber": "H", "chamber_id": 31, "name": "Consumer Protection & Commerce"}, {"date": "2021-02-19", "committee_id": 2039, "chamber": "H", "chamber_id": 31, "name": "Finance"}, {"date": "2021-03-09", "committee_id": 2058, "chamber": "S", "chamber_id": 32, "name": "Human Services"}, {"date": "2021-03-25", "committee_id": 3756, "chamber": "S", "chamber_id": 32, "name": "Judiciary"}], "history": [{"date": "2021-01-25", "action": "Pending introduction.", "chamber": "H", "chamber_id": 31, "importance": 0}, {"date": "2021-01-27", "action": "Introduced and Pass First Reading.", "chamber": "H", "chamber_id": 31, "importance": 1}, {"date": "2021-01-27", "action": "Referred to HHH, CPC, FIN, referral sheet 1", "chamber": "H", "chamber_id": 31, "importance": 1}, {"date": "2021-02-02", "action": "Bill scheduled to be heard by HHH on Friday, 02-05-21 8:30AM in House conference room Via Videoconference.", "chamber": "H", "chamber_id": 31, "importance": 0}, {"date": "2021-02-05", "action": "The committees on HHH recommend that the measure be PASSED, WITH AMENDMENTS. The votes were as follows: 7 Ayes: Representative(s) Yamane, Tam, Har, Kapela, LoPresti, Nishimoto, Ward; Ayes with reservations: none; Noes: none; and 1 Excused: Representative(s) Gates.", "chamber": "H", "chamber_id": 31, "importance": 0}, {"date": "2021-02-10", "action": "Reported from HHH (Stand. Com. Rep. No. 133) as amended in HD 1, recommending passage on Second Reading and referral to CPC.", "chamber": "H", "chamber_id": 31, "importance": 1}, {"date": "2021-02-10", "action": "Passed Second Reading as amended in HD 1 and referred to the committee(s) on CPC with none voting aye with reservations; none voting no (0) and Representative(s) Eli excused (1).", "chamber": "H", "chamber_id": 31, "importance": 1}, {"date": "2021-02-12", "action": "Bill scheduled to be heard by CPC on Wednesday, 02-17-21 2:00PM in House conference room 329 Via Videoconference.", "chamber": "H", "chamber_id": 31, "importance": 0}, {"date": "2021-02-17", "action": "The committees on CPC recommend that the measure be PASSED, UNAMENDED. The votes were as follows: 10 Ayes: Representative(s) Johanson, Kitagawa, Aquino, Hashem, Kong, Mizuno, Morikawa, Onishi, Tarnas, Matsumoto; Ayes with reservations: none; Noes: none; and 1 Excused: Representative(s) Har.", "chamber": "H", "chamber_id": 31, "importance": 0}, {"date": "2021-02-19", "action": "Reported from CPC (Stand. Com. Rep. No. 628), recommending referral to FIN.", "chamber": "H", "chamber_id": 31, "importance": 1}, {"date": "2021-02-19", "action": "Report adopted; referred to the committee(s) on FIN with none voting aye with reservations; none voting no (0) and Representative(s) Har, Kong, Matayoshi excused (3).", "chamber": "H", "chamber_id": 31, "importance": 1}, {"date": "2021-02-23", "action": "Bill scheduled to be heard by FIN on Friday, 02-26-21 11:00AM in House conference room 308 Via Videoconference.", "chamber": "H", "chamber_id": 31, "importance": 0}, {"date": "2021-02-26", "action": "The committees on FIN recommend that the measure be PASSED, UNAMENDED. The votes were as follows: 14 Ayes: Representative(s) Luke, Cullen, Branco, Eli, Holt, Ilagan, B. Kobayashi, Marten, Perruso, Sayama, Tam, Wildberger, Yamashita, McDermott; Ayes with reservations: none; Noes: none; and 1 Excused: Representative(s) Nishimoto.", "chamber": "H", "chamber_id": 31, "importance": 0}, {"date": "2021-03-05", "action": "Reported from FIN (Stand. Com. Rep. No. 802), recommending passage on Third Reading.", "chamber": "H", "chamber_id": 31, "importance": 1}, {"date": "2021-03-05", "action": "Passed Third Reading with none voting aye with reservations; none voting no (0) and Representative(s) McKelvey excused (1). Transmitted to Senate.", "chamber": "H", "chamber_id": 31, "importance": 1}, {"date": "2021-03-09", "action": "Received from House (Hse. Com. No. 133).", "chamber": "S", "chamber_id": 32, "importance": 0}, {"date": "2021-03-09", "action": "Passed First Reading.", "chamber": "S", "chamber_id": 32, "importance": 0}, {"date": "2021-03-09", "action": "Referred to HMS/LCA, JDC/WAM.", "chamber": "S", "chamber_id": 32, "importance": 1}, {"date": "2021-03-17", "action": "The committee(s) on HMS/LCA has scheduled a public hearing on 03-23-21 3:00PM; CR 225 &amp; Videoconference.", "chamber": "S", "chamber_id": 32, "importance": 0}, {"date": "2021-03-23", "action": "The committee(s) on LCA recommend(s) that the measure be PASSED, WITH AMENDMENTS. The votes in LCA were as follows: 5 Aye(s): Senator(s) Taniguchi, Ihara, Chang, Keohokalole, Fevella; Aye(s) with reservations: none ; 0 No(es): none; and 0 Excused: none.", "chamber": "S", "chamber_id": 32, "importance": 0}, {"date": "2021-03-23", "action": "The committee(s) on HMS recommend(s) that the measure be PASSED, WITH AMENDMENTS. The votes in HMS were as follows: 5 Aye(s): Senator(s) San Buenaventura, Ihara, Acasio, Misalucha, Fevella; Aye(s) with reservations: none ; 0 No(es): none; and 0 Excused: none.", "chamber": "S", "chamber_id": 32, "importance": 0}, {"date": "2021-03-25", "action": "Reported from HMS/LCA (Stand. Com. Rep. No. 1253) with recommendation of passage on Second Reading, as amended (SD 1) and referral to JDC/WAM.", "chamber": "S", "chamber_id": 32, "importance": 1}, {"date": "2021-03-25", "action": "Report adopted; Passed Second Reading, as amended (SD 1) and referred to JDC/WAM.", "chamber": "S", "chamber_id": 32, "importance": 1}], "sponsors": [{"people_id": 8337, "person_hash": "hg4f4vxf", "party_id": "1", "state_id": 11, "party": "D", "role_id": 1, "role": "Rep", "name": "Scott Nishimoto", "first_name": "Scott", "middle_name": "Y.", "last_name": "Nishimoto", "suffix": "", "nickname": "", "district": "HD-021", "ftm_eid": 12999415, "votesmart_id": 32355, "opensecrets_id": "", "knowwho_pid": 211939, "ballotpedia": "Scott_Nishimoto", "sponsor_type_id": 1, "sponsor_order": 1, "committee_sponsor": 0, "committee_id": 0, "state_federal": 0}, {"people_id": 8389, "person_hash": "3z1jj3oe", "party_id": "1", "state_id": 11, "party": "D", "role_id": 1, "role": "Rep", "name": "Della au Belatti", "first_name": "Della", "middle_name": "", "last_name": "au Belatti", "suffix": "", "nickname": "", "district": "HD-024", "ftm_eid": 6481341, "votesmart_id": 67629, "opensecrets_id": "", "knowwho_pid": 249221, "ballotpedia": "Della_Au_Belatti", "sponsor_type_id": 1, "sponsor_order": 2, "committee_sponsor": 0, "committee_id": 0, "state_federal": 0}, {"people_id": 19023, "person_hash": "2cuc92yn", "party_id": "1", "state_id": 11, "party": "D", "role_id": 1, "role": "Rep", "name": "Daniel Holt", "first_name": "Daniel", "middle_name": "", "last_name": "Holt", "suffix": "", "nickname": "", "district": "HD-029", "ftm_eid": 13689942, "votesmart_id": 140605, "opensecrets_id": "", "knowwho_pid": 410562, "ballotpedia": "Daniel_Holt", "sponsor_type_id": 1, "sponsor_order": 3, "committee_sponsor": 0, "committee_id": 0, "state_federal": 0}, {"people_id": 22564, "person_hash": "67pro37i", "party_id": "1", "state_id": 11, "party": "D", "role_id": 1, "role": "Rep", "name": "Greggor Ilagan", "first_name": "Greggor", "middle_name": "", "last_name": "Ilagan", "suffix": "", "nickname": "", "district": "HD-004", "ftm_eid": 21264862, "votesmart_id": 157776, "opensecrets_id": "", "knowwho_pid": 569176, "ballotpedia": "Greggor_Ilagan", "sponsor_type_id": 1, "sponsor_order": 4, "committee_sponsor": 0, "committee_id": 0, "state_federal": 0}, {"people_id": 17298, "person_hash": "kzbukyql", "party_id": "1", "state_id": 11, "party": "D", "role_id": 1, "role": "Rep", "name": "Matthew Lopresti", "first_name": "Matthew", "middle_name": "", "last_name": "Lopresti", "suffix": "", "nickname": "", "district": "HD-041", "ftm_eid": 13689951, "votesmart_id": 140620, "opensecrets_id": "", "knowwho_pid": 424278, "ballotpedia": "Matt_LoPresti", "sponsor_type_id": 1, "sponsor_order": 5, "committee_sponsor": 0, "committee_id": 0, "state_federal": 0}, {"people_id": 19024, "person_hash": "v8bomq38", "party_id": "1", "state_id": 11, "party": "D", "role_id": 1, "role": "Rep", "name": "Sean Quinlan", "first_name": "Sean", "middle_name": "", "last_name": "Quinlan", "suffix": "", "nickname": "", "district": "HD-047", "ftm_eid": 40622434, "votesmart_id": 172307, "opensecrets_id": "", "knowwho_pid": 580946, "ballotpedia": "Sean_Quinlan_(Hawaii)", "sponsor_type_id": 1, "sponsor_order": 6, "committee_sponsor": 0, "committee_id": 0, "state_federal": 0}, {"people_id": 15005, "person_hash": "wc8zxrqy", "party_id": "1", "state_id": 11, "party": "D", "role_id": 1, "role": "Rep", "name": "Gregg Takayama", "first_name": "Gregg", "middle_name": "", "last_name": "Takayama", "suffix": "", "nickname": "", "district": "HD-034", "ftm_eid": 13689946, "votesmart_id": 140608, "opensecrets_id": "", "knowwho_pid": 410574, "ballotpedia": "Gregg_Takayama", "sponsor_type_id": 1, "sponsor_order": 7, "committee_sponsor": 0, "committee_id": 0, "state_federal": 0}, {"people_id": 8386, "person_hash": "pmfbvdr9", "party_id": "1", "state_id": 11, "party": "D", "role_id": 1, "role": "Rep", "name": "Ryan Yamane", "first_name": "Ryan", "middle_name": "I.", "last_name": "Yamane", "suffix": "", "nickname": "", "district": "HD-037", "ftm_eid": 6401313, "votesmart_id": 32298, "opensecrets_id": "", "knowwho_pid": 227433, "ballotpedia": "Ryan_Yamane", "sponsor_type_id": 1, "sponsor_order": 8, "committee_sponsor": 0, "committee_id": 0, "state_federal": 0}], "sasts": [], "subjects": [{"subject_id": 180010, "subject_name": "Public Assistance"}, {"subject_id": 178979, "subject_name": "Employers"}, {"subject_id": 178535, "subject_name": "Employees"}, {"subject_id": 176940, "subject_name": "Report"}, {"subject_id": 176240, "subject_name": "Department of Human Services"}, {"subject_id": 177418, "subject_name": "Department of Labor and Industrial Relations"}], "texts": [{"doc_id": 2257573, "date": "2021-01-25", "type": "Introduced", "type_id": 1, "mime": "text/html", "mime_id": 1, "url": "https://legiscan.com/HI/text/HB718/id/2257573", "state_link": "https://www.capitol.hawaii.gov/session2021/bills/HB718_.HTM", "text_size": 16378, "text_hash": "63e14a26dda31f3a5939ea47c9ce9c4b"}, {"doc_id": 2283712, "date": "2021-02-09", "type": "Amended", "type_id": 3, "mime": "text/html", "mime_id": 1, "url": "https://legiscan.com/HI/text/HB718/id/2283712", "state_link": "https://www.capitol.hawaii.gov/session2021/bills/HB718_HD1_.HTM", "text_size": 15270, "text_hash": "9fd4d466919dc979070a59c733ac472a"}, {"doc_id": 2347158, "date": "2021-03-25", "type": "Amended", "type_id": 3, "mime": "text/html", "mime_id": 1, "url": "https://legiscan.com/HI/text/HB718/id/2347158", "state_link": "https://www.capitol.hawaii.gov/session2021/bills/HB718_SD1_.HTM", "text_size": 15070, "text_hash": "0ab6a5e822a82992e3d60bbb40e7e2bc"}], "votes": [{"roll_call_id": 997331, "date": "2021-02-05", "desc": "House Health, Human Services, & Homelessness: Passed, With Amendments", "yea": 7, "nay": 0, "nv": 0, "absent": 1, "total": 8, "passed": 1, "chamber": "H", "chamber_id": 31, "url": "https://legiscan.com/HI/rollcall/HB718/id/997331", "state_link": "https://www.capitol.hawaii.gov/measure_indiv.aspx?billtype=HB&billnumber=718&year=2021"}, {"roll_call_id": 1008260, "date": "2021-02-17", "desc": "House Consumer Protection & Commerce: Passed, Unamended", "yea": 10, "nay": 0, "nv": 0, "absent": 1, "total": 11, "passed": 1, "chamber": "H", "chamber_id": 31, "url": "https://legiscan.com/HI/rollcall/HB718/id/1008260", "state_link": "https://www.capitol.hawaii.gov/measure_indiv.aspx?billtype=HB&billnumber=718&year=2021"}, {"roll_call_id": 1017120, "date": "2021-02-26", "desc": "House Finance: Passed, Unamended", "yea": 14, "nay": 0, "nv": 0, "absent": 1, "total": 15, "passed": 1, "chamber": "H", "chamber_id": 31, "url": "https://legiscan.com/HI/rollcall/HB718/id/1017120", "state_link": "https://www.capitol.hawaii.gov/measure_indiv.aspx?billtype=HB&billnumber=718&year=2021"}, {"roll_call_id": 1035111, "date": "2021-03-23", "desc": "Senate Labor, Culture and the Arts: Passed, With Amendments", "yea": 5, "nay": 0, "nv": 0, "absent": 0, "total": 5, "passed": 1, "chamber": "S", "chamber_id": 32, "url": "https://legiscan.com/HI/rollcall/HB718/id/1035111", "state_link": "https://www.capitol.hawaii.gov/measure_indiv.aspx?billtype=HB&billnumber=718&year=2021"}, {"roll_call_id": 1035112, "date": "2021-03-23", "desc": "Senate Human Services: Passed, With Amendments", "yea": 5, "nay": 0, "nv": 0, "absent": 0, "total": 5, "passed": 1, "chamber": "S", "chamber_id": 32, "url": "https://legiscan.com/HI/rollcall/HB718/id/1035112", "state_link": "https://www.capitol.hawaii.gov/measure_indiv.aspx?billtype=HB&billnumber=718&year=2021"}], "amendments": [], "supplements": [], "calendar": [{"type_id": 1, "type": "Hearing", "date": "2021-02-05", "time": "08:30", "location": "Conference Room Via Videoconference", "description": "House Health, Human Services, & Homelessness Hearing"}, {"type_id": 1, "type": "Hearing", "date": "2021-02-17", "time": "14:00", "location": "Conference Room 329 Via Videoconference", "description": "House Consumer Protection & Commerce Hearing"}, {"type_id": 1, "type": "Hearing", "date": "2021-02-26", "time": "11:00", "location": "Conference Room 308 Via Videoconference", "description": "House Finance Hearing"}]}}