{"status": "OK", "bill": {"bill_id": 801696, "change_hash": "7e34ff4056c855106163654005cd60e8", "session_id": 1187, "session": {"session_id": 1187, "state_id": 46, "year_start": 2016, "year_end": 2016, "prefile": 0, "sine_die": 1, "prior": 1, "special": 0, "session_tag": "Regular Session", "session_title": "2016 Regular Session", "session_name": "2016 Regular Session"}, "url": "https://legiscan.com/VA/bill/SB64/2016", "state_link": "https://lis.virginia.gov/cgi-bin/legp604.exe?161+sum+SB64", "completed": 1, "status": 4, "status_date": "2016-04-06", "progress": [{"date": "2015-12-19", "event": 1}, {"date": "2015-12-19", "event": 9}, {"date": "2016-02-09", "event": 10}, {"date": "2016-02-11", "event": 2}, {"date": "2016-02-15", "event": 9}, {"date": "2016-02-22", "event": 10}, {"date": "2016-02-25", "event": 3}, {"date": "2016-04-06", "event": 8}, {"date": "2016-04-06", "event": 4}], "state": "VA", "state_id": 46, "bill_number": "SB64", "bill_type": "B", "bill_type_id": "1", "body": "S", "body_id": 8, "current_body": "", "current_body_id": 0, "title": "Retail Sales and Use Tax; exemption for certain data centers.", "description": "Sales and use tax exemption; certain data centers. Extends the sunset date for the sales and use tax exemption for certain data centers from June 30, 2020, to June 30, 2035, and eliminates the sunset date of June 30, 2020, for provisions of the existing law that allow the owner of the data center to count the jobs created and investments made by tenants to count toward the overall jobs and investment criteria for the exemption. If an entity previously created 50 new jobs at a data center in the Commonwealth in order to qualify for the exemption, those 50 jobs may be relocated to a new data center in the Commonwealth with a capital investment of at least $500 million on or after July 1, 2016, and count toward the new jobs requirement for the new data center to qualify for the exemption. The bill also makes a technical correction regarding a subdivision that is erroneously set out twice in the Code.", "pending_committee_id": 0, "committee": [], "referrals": [{"date": "2015-12-19", "committee_id": 164, "chamber": "S", "chamber_id": 8, "name": "Finance and Appropriations"}, {"date": "2016-02-16", "committee_id": 3868, "chamber": "H", "chamber_id": 7, "name": "Finance: Subcommittee #2"}], "history": [{"date": "2015-12-19", "action": "Prefiled and ordered printed; offered 01/13/16 16102384D", "chamber": "S", "chamber_id": 8, "importance": 0}, {"date": "2015-12-19", "action": "Referred to Committee on Finance", "chamber": "S", "chamber_id": 8, "importance": 1}, {"date": "2016-02-09", "action": "Reported from Finance with substitute (15-Y 0-N)", "chamber": "S", "chamber_id": 8, "importance": 1}, {"date": "2016-02-09", "action": "Committee substitute printed 16105371D-S1", "chamber": "S", "chamber_id": 8, "importance": 0}, {"date": "2016-02-10", "action": "Constitutional reading dispensed (40-Y 0-N)", "chamber": "S", "chamber_id": 8, "importance": 0}, {"date": "2016-02-11", "action": "Read second time", "chamber": "S", "chamber_id": 8, "importance": 0}, {"date": "2016-02-11", "action": "Reading of substitute waived", "chamber": "S", "chamber_id": 8, "importance": 0}, {"date": "2016-02-11", "action": "Committee substitute agreed to 16105371D-S1", "chamber": "S", "chamber_id": 8, "importance": 0}, {"date": "2016-02-11", "action": "Engrossed by Senate - committee substitute SB64S1", "chamber": "S", "chamber_id": 8, "importance": 1}, {"date": "2016-02-11", "action": "Constitutional reading dispensed (40-Y 0-N)", "chamber": "S", "chamber_id": 8, "importance": 0}, {"date": "2016-02-11", "action": "Passed Senate (40-Y 0-N)", "chamber": "S", "chamber_id": 8, "importance": 0}, {"date": "2016-02-15", "action": "Placed on Calendar", "chamber": "H", "chamber_id": 7, "importance": 0}, {"date": "2016-02-15", "action": "Read first time", "chamber": "H", "chamber_id": 7, "importance": 0}, {"date": "2016-02-15", "action": "Referred to Committee on Finance", "chamber": "H", "chamber_id": 7, "importance": 1}, {"date": "2016-02-16", "action": "Assigned Finance sub: Subcommittee #2", "chamber": "H", "chamber_id": 7, "importance": 0}, {"date": "2016-02-17", "action": "Subcommittee recommends reporting (10-Y 1-N)", "chamber": "H", "chamber_id": 7, "importance": 0}, {"date": "2016-02-22", "action": "Reported from Finance (21-Y 1-N)", "chamber": "H", "chamber_id": 7, "importance": 1}, {"date": "2016-02-23", "action": "Read second time", "chamber": "H", "chamber_id": 7, "importance": 0}, {"date": "2016-02-24", "action": "Read third time", "chamber": "H", "chamber_id": 7, "importance": 0}, {"date": "2016-02-24", "action": "Passed House (97-Y 1-N 2-A)", "chamber": "H", "chamber_id": 7, "importance": 0}, {"date": "2016-02-24", "action": "VOTE: PASSAGE (97-Y 1-N 2-A)", "chamber": "H", "chamber_id": 7, "importance": 0}, {"date": "2016-02-25", "action": "Enrolled", "chamber": "S", "chamber_id": 8, "importance": 1}, {"date": "2016-02-25", "action": "Bill text as passed Senate and House (SB64ER)", "chamber": "S", "chamber_id": 8, "importance": 0}, {"date": "2016-02-25", "action": "Signed by Speaker", "chamber": "H", "chamber_id": 7, "importance": 0}, {"date": "2016-02-26", "action": "Signed by President", "chamber": "S", "chamber_id": 8, "importance": 0}, {"date": "2016-02-29", "action": "Enrolled Bill Communicated to Governor on 2/29/16", "chamber": "S", "chamber_id": 8, "importance": 0}, {"date": "2016-02-29", "action": "Governor: Governor's Action Deadline Midnight, March 7, 2016", "chamber": "", "chamber_id": 0, "importance": 0}, {"date": "2016-03-07", "action": "Governor's recommendation received by Senate", "chamber": "S", "chamber_id": 8, "importance": 0}, {"date": "2016-03-09", "action": "Senate rejected Governor's recommendation (0-Y 40-N)", "chamber": "S", "chamber_id": 8, "importance": 0}, {"date": "2016-03-11", "action": "Communicated to Governor", "chamber": "S", "chamber_id": 8, "importance": 0}, {"date": "2016-04-06", "action": "Governor: Approved by Governor-Chapter 712 (effective 7/1/16)", "chamber": "", "chamber_id": 0, "importance": 1}, {"date": "2016-04-06", "action": "Governor: Acts of Assembly Chapter text (CHAP0712)", "chamber": "", "chamber_id": 0, "importance": 0}], "sponsors": [{"people_id": 789, "person_hash": "9ju7o265", "party_id": "2", "state_id": 46, "party": "R", "role_id": 2, "role": "Sen", "name": "Frank Ruff", "first_name": "Frank", "middle_name": "M.", "last_name": "Ruff", "suffix": "Jr.", "nickname": "", "district": "SD-015", "ftm_eid": 6571545, "votesmart_id": 5188, "opensecrets_id": "", "knowwho_pid": 199483, "ballotpedia": "Frank_Ruff", "sponsor_type_id": 1, "sponsor_order": 1, "committee_sponsor": 0, "committee_id": 0, "state_federal": 0}], "sasts": [{"type_id": 1, "type": "Same As", "sast_bill_number": "HB872", "sast_bill_id": 812443}], "subjects": [], "texts": [{"doc_id": 1279582, "date": "2015-12-19", "type": "Prefiled", "type_id": 11, "mime": "text/html", "mime_id": 1, "url": "https://legiscan.com/VA/text/SB64/id/1279582", "state_link": "https://lis.virginia.gov/cgi-bin/legp604.exe?161+ful+SB64+hil", "text_size": 16662, "text_hash": "acc41c8af14c39fa290ecb854a235d0a"}, {"doc_id": 1332063, "date": "2016-02-09", "type": "Comm Sub", "type_id": 2, "mime": "text/html", "mime_id": 1, "url": "https://legiscan.com/VA/text/SB64/id/1332063", "state_link": "https://lis.virginia.gov/cgi-bin/legp604.exe?161+ful+SB64S1+hil", "text_size": 16926, "text_hash": "7a810ac3b32925501fa9e8c311fbd913"}, {"doc_id": 1351402, "date": "2016-02-25", "type": "Enrolled", "type_id": 5, "mime": "text/html", "mime_id": 1, "url": "https://legiscan.com/VA/text/SB64/id/1351402", "state_link": "https://lis.virginia.gov/cgi-bin/legp604.exe?161+ful+SB64ER+hil", "text_size": 16772, "text_hash": "084922c9320a497daf1ec13d0c147213"}, {"doc_id": 1392848, "date": "2016-04-06", "type": "Chaptered", "type_id": 6, "mime": "text/html", "mime_id": 1, "url": "https://legiscan.com/VA/text/SB64/id/1392848", "state_link": "https://lis.virginia.gov/cgi-bin/legp604.exe?161+ful+CHAP0712+hil", "text_size": 16765, "text_hash": "c7fdd56ee60f5ede6bf66259623eab88"}], "votes": [{"roll_call_id": 493145, "date": "2016-02-09", "desc": "Senate: Reported from Finance with substitute (15-Y 0-N)", "yea": 15, "nay": 0, "nv": 0, "absent": 0, "total": 15, "passed": 1, "chamber": "S", "chamber_id": 8, "url": "https://legiscan.com/VA/rollcall/SB64/id/493145", "state_link": "https://lis.virginia.gov/cgi-bin/legp604.exe?161+vot+S05V0072+SB0064"}, {"roll_call_id": 494730, "date": "2016-02-10", "desc": "Senate: Constitutional reading dispensed (40-Y 0-N)", "yea": 40, "nay": 0, "nv": 0, "absent": 0, "total": 40, "passed": 1, "chamber": "S", "chamber_id": 8, "url": "https://legiscan.com/VA/rollcall/SB64/id/494730", "state_link": "https://lis.virginia.gov/cgi-bin/legp604.exe?161+vot+SV0313SB0064+SB0064"}, {"roll_call_id": 495781, "date": "2016-02-11", "desc": "Senate: Constitutional reading dispensed (40-Y 0-N)", "yea": 40, "nay": 0, "nv": 0, "absent": 0, "total": 40, "passed": 1, "chamber": "S", "chamber_id": 8, "url": "https://legiscan.com/VA/rollcall/SB64/id/495781", "state_link": "https://lis.virginia.gov/cgi-bin/legp604.exe?161+vot+SV0331SB0064+SB0064"}, {"roll_call_id": 495782, "date": "2016-02-11", "desc": "Senate: Passed Senate (40-Y 0-N)", "yea": 40, "nay": 0, "nv": 0, "absent": 0, "total": 40, "passed": 1, "chamber": "S", "chamber_id": 8, "url": "https://legiscan.com/VA/rollcall/SB64/id/495782", "state_link": "https://lis.virginia.gov/cgi-bin/legp604.exe?161+vot+SV0332SB0064+SB0064"}, {"roll_call_id": 499664, "date": "2016-02-17", "desc": "House: Subcommittee recommends reporting (10-Y 1-N)", "yea": 10, "nay": 1, "nv": 0, "absent": 0, "total": 11, "passed": 1, "chamber": "H", "chamber_id": 7, "url": "https://legiscan.com/VA/rollcall/SB64/id/499664", "state_link": "https://lis.virginia.gov/cgi-bin/legp604.exe?161+vot+H1002V0039+SB0064"}, {"roll_call_id": 503271, "date": "2016-02-22", "desc": "House: Reported from Finance (21-Y 1-N)", "yea": 21, "nay": 1, "nv": 0, "absent": 0, "total": 22, "passed": 1, "chamber": "H", "chamber_id": 7, "url": "https://legiscan.com/VA/rollcall/SB64/id/503271", "state_link": "https://lis.virginia.gov/cgi-bin/legp604.exe?161+vot+H10V0146+SB0064"}, {"roll_call_id": 505885, "date": "2016-02-24", "desc": "House: VOTE: PASSAGE (97-Y 1-N 2-A)", "yea": 100, "nay": 1, "nv": 0, "absent": 2, "total": 103, "passed": 1, "chamber": "H", "chamber_id": 7, "url": "https://legiscan.com/VA/rollcall/SB64/id/505885", "state_link": "https://lis.virginia.gov/cgi-bin/legp604.exe?161+vot+HV0864+SB0064"}, {"roll_call_id": 516821, "date": "2016-03-09", "desc": "Senate: Senate rejected Governor's recommendation (0-Y 40-N)", "yea": 0, "nay": 40, "nv": 0, "absent": 0, "total": 40, "passed": 0, "chamber": "S", "chamber_id": 8, "url": "https://legiscan.com/VA/rollcall/SB64/id/516821", "state_link": "https://lis.virginia.gov/cgi-bin/legp604.exe?161+vot+SV0975SB0064+SB0064"}], "amendments": [], "supplements": [], "calendar": [{"type_id": 1, "type": "Hearing", "date": "2016-02-03", "time": "09:00", "location": "Senate Room B", "description": "Senate Committee on Finance Hearing"}, {"type_id": 1, "type": "Hearing", "date": "2016-02-09", "time": "09:00", "location": "Senate Room B", "description": "Senate Committee on Finance Hearing"}, {"type_id": 1, "type": "Hearing", "date": "2016-02-17", "time": "00:00", "location": "5th Floor East Conference Room", "description": "House Finance - Subcommittee #2 Committee Hearing"}, {"type_id": 1, "type": "Hearing", "date": "2016-02-22", "time": "08:30", "location": "9th Floor Appropriations Conference Room, GAB", "description": "House Finance Committee Hearing"}]}}