{"status": "OK", "bill": {"bill_id": 1102353, "change_hash": "9bea266c1b17e9daa0d63fe42123ede6", "session_id": 1397, "session": {"session_id": 1397, "state_id": 2, "year_start": 2017, "year_end": 2018, "prefile": 0, "sine_die": 1, "prior": 1, "special": 0, "session_tag": "Regular Session", "session_title": "2017-2018 Regular Session", "session_name": "30th Legislature"}, "url": "https://legiscan.com/AK/bill/SJR15/2017", "state_link": "http://www.akleg.gov/basis/Bill/Detail/30?Root=SJR15", "completed": 0, "status": 1, "status_date": "2018-03-07", "progress": [{"date": "2018-03-07", "event": 1}, {"date": "2018-03-07", "event": 9}], "state": "AK", "state_id": 2, "bill_number": "SJR15", "bill_type": "JR", "bill_type_id": "4", "body": "S", "body_id": 14, "current_body": "S", "current_body_id": 14, "title": "Fed Employees Obey Law Re: Drugs; Tongass", "description": "Urging federal government employees to follow lawful Acts of the United States Congress; urging the federal government to terminate federal agency employees who fail to follow the law; and urging the United States Secretary of Agriculture to review the actions of and inaction by the United States Forest Service relating to unlawful management of the Tongass National Forest in ways that are damaging to citizens of Alaska.", "pending_committee_id": 2145, "committee": {"committee_id": 2145, "chamber": "S", "chamber_id": 14, "name": "Judiciary"}, "referrals": [{"date": "2018-03-07", "committee_id": 2145, "chamber": "S", "chamber_id": 14, "name": "Judiciary"}], "history": [{"date": "2018-03-07", "action": "READ THE FIRST TIME - REFERRALS", "chamber": "S", "chamber_id": 14, "importance": 1}, {"date": "2018-03-07", "action": "JUD", "chamber": "S", "chamber_id": 14, "importance": 1}, {"date": "2018-03-07", "action": "REFERRED TO JUDICIARY", "chamber": "S", "chamber_id": 14, "importance": 0}], "sponsors": [], "sasts": [], "subjects": [{"subject_id": 4484, "subject_name": "Crimes"}, {"subject_id": 4506, "subject_name": "Criminal Procedure"}, {"subject_id": 4642, "subject_name": "Drugs"}, {"subject_id": 4669, "subject_name": "Easements"}, {"subject_id": 4690, "subject_name": "Economy"}, {"subject_id": 4522, "subject_name": "Environmental Concerns"}, {"subject_id": 4564, "subject_name": "Executive Branch"}, {"subject_id": 4524, "subject_name": "Forestry"}, {"subject_id": 4629, "subject_name": "Intergovernmental Relations"}, {"subject_id": 4525, "subject_name": "Land"}, {"subject_id": 4509, "subject_name": "Law Enforcement"}, {"subject_id": 4547, "subject_name": "Planning"}, {"subject_id": 4558, "subject_name": "Public Employees"}, {"subject_id": 4600, "subject_name": "Public Land"}, {"subject_id": 4635, "subject_name": "Regulations"}, {"subject_id": 4670, "subject_name": "Regulatory Actions"}], "texts": [{"doc_id": 1753636, "date": "2018-03-07", "type": "Introduced", "type_id": 1, "mime": "application/pdf", "mime_id": 2, "url": "https://legiscan.com/AK/text/SJR15/id/1753636", "state_link": "http://www.legis.state.ak.us/PDF/30/Bills/SJR015A.PDF", "text_size": 487327, "text_hash": "9e0b7f5177f2707cfd29c3b1eab6fa9c"}], "votes": [], "amendments": [], "supplements": [], "calendar": []}}